rfmanalysis/__init__.py
rfmanalysis/rfmanalysis.py
rfmanalysis-0.2.0.dist-info/AUTHORS.rst
rfmanalysis-0.2.0.dist-info/LICENSE
rfmanalysis-0.2.0.dist-info/METADATA
rfmanalysis-0.2.0.dist-info/WHEEL
rfmanalysis-0.2.0.dist-info/top_level.txt
rfmanalysis-0.2.0.dist-info/RECORD
