Metadata-Version: 2.1
Name: rfmanalysis
Version: 0.2.0
Summary: This repository contains a Python implementation of RFM (Recency, Frequency, Monetary) analysis, a customer segmentation technique used in marketing and customer relationship management. The RFM analysis helps identify customer segments based on their purchasing behavior, allowing businesses to tailor their marketing strategies and customer retention efforts.
Home-page: https://github.com/emmayann/rfmanalysis
Author: Emma Hovhannisyan
Author-email: emmahovhannisyan02@gmail.com
License: MIT license
Keywords: rfmanalysis
Classifier: Development Status :: 2 - Pre-Alpha
Classifier: Intended Audience :: Developers
Classifier: License :: OSI Approved :: MIT License
Classifier: Natural Language :: English
Classifier: Programming Language :: Python :: 3
Classifier: Programming Language :: Python :: 3.6
Classifier: Programming Language :: Python :: 3.7
Classifier: Programming Language :: Python :: 3.8
Requires-Python: >=3.6
License-File: LICENSE
License-File: AUTHORS.rst
